{
  "title": "Requisitos da Estrutura",
  "text": [
    {
      "text": "Sua fundição tem alguns requisitos. Se for muito grande, ela se torna tão ineficiente que você precisaria de uma torre de tanques de combustível maior do que a própria fundição para operá-la."
    },
    {
      "text": "Sua fundição deve ter um piso feito de blocos de fundição aceitáveis, excluindo o vidro. Os blocos aceitáveis serão mostrados nas próximas páginas! Sua fundição também deve ser retangular, não pode ser em formato de L, círculo ou dodecaedro.",
      "paragraph": true
    },
    {
      "text": "O tamanho máximo da sua fundição é de 16x16x65 externamente, ou 14x14x64 internamente.",
      "paragraph": true
    }
  ]
}
